napari_rosettasciio/__init__.py
napari_rosettasciio/_dialogs.py
napari_rosettasciio/_reader.py
napari_rosettasciio/_version.py
napari_rosettasciio/_writer.py
napari_rosettasciio/napari.yaml
napari_rosettasciio-0.1.1.dist-info/licenses/LICENSE
napari_rosettasciio-0.1.1.dist-info/METADATA
napari_rosettasciio-0.1.1.dist-info/WHEEL
napari_rosettasciio-0.1.1.dist-info/entry_points.txt
napari_rosettasciio-0.1.1.dist-info/top_level.txt
napari_rosettasciio-0.1.1.dist-info/RECORD
