Metadata-Version: 2.4
Name: napari-rosettasciio
Version: 0.1.1
Summary: A napari plugin to read and write scientific data formats using RosettaSciIO
Author: Jules Vanaret
Author-email: jules.vanaret@epfl.ch
License: 
Classifier: Development Status :: 3 - Alpha
Classifier: Framework :: napari
Classifier: Intended Audience :: Developers
Classifier: Intended Audience :: Science/Research
Classifier: License :: OSI Approved :: MIT License
Classifier: Operating System :: OS Independent
Classifier: Programming Language :: Python
Classifier: Programming Language :: Python :: 3
Classifier: Programming Language :: Python :: 3 :: Only
Classifier: Programming Language :: Python :: 3.10
Classifier: Programming Language :: Python :: 3.11
Classifier: Programming Language :: Python :: 3.12
Classifier: Programming Language :: Python :: 3.13
Classifier: Topic :: Scientific/Engineering
Classifier: Topic :: Scientific/Engineering :: Image Processing
Requires-Python: >=3.10
License-File: LICENSE
Requires-Dist: numpy>=1.22
Requires-Dist: rosettasciio>=0.1
Requires-Dist: PyQt5
Requires-Dist: qtpy
Provides-Extra: all
Requires-Dist: rosettasciio[all]; extra == "all"
Provides-Extra: hdf5
Requires-Dist: rosettasciio[hdf5]; extra == "hdf5"
Provides-Extra: image
Requires-Dist: rosettasciio[image]; extra == "image"
Provides-Extra: zspy
Requires-Dist: rosettasciio[zspy]; extra == "zspy"
Provides-Extra: mrcz
Requires-Dist: rosettasciio[mrcz]; extra == "mrcz"
Provides-Extra: usid
Requires-Dist: rosettasciio[usid]; extra == "usid"
Dynamic: license-file
